{
  "items": [
    {
      "name": "Meriol chan（@meriol_chan）さん - きれいなお姉さん無修正",
      "id": "meriol_chan",
      "insta": "https://www.instagram.com/smol_meri/",
      "images": [
        "https://x8.shinobi.jp/bin/ll?100057901",
        "https://blog-imgs-145-origin.2nt.com/r/e/i/reinasex/Meriol-Chan-Ada-Wong-01s.jpg",
        "https://blog-imgs-145-origin.2nt.com/r/e/i/reinasex/Meriol-Chan-Ada-Wong-16s.jpg"
      ],
      "url": "https://reinasex.blog.2nt.com/blog-entry-1779.html",
      "source": "reinasex"
    },
    {
      "name": "浵卡Tokar🔞（@laurus0711）さん - きれいなお姉さん無修正",
      "id": "laurus0711",
      "insta": "https://www.instagram.com/_minncoco/",
      "images": [
        "https://x8.shinobi.jp/bin/ll?100057901",
        "https://blog-imgs-145-origin.2nt.com/r/e/i/reinasex/Tokar-Ubel-01.jpg",
        "https://blog-imgs-145-origin.2nt.com/r/e/i/reinasex/Tokar-Ubel-04.jpg"
      ],
      "url": "https://reinasex.blog.2nt.com/blog-entry-1773.html",
      "source": "reinasex"
    },
    {
      "name": "KaYa Huang（萱）（@kaya1028）さん - きれいなお姉さん無修正",
      "id": "Kayaaa1028",
      "insta": "https://www.instagram.com/kaya_huang/?hl=ja",
      "images": [
        "https://x8.shinobi.jp/bin/ll?100057901",
        "https://blog-imgs-145-origin.2nt.com/r/e/i/reinasex/KaYa-Huang-Atago-Race-Queen-20s.jpg",
        "https://blog-imgs-145-origin.2nt.com/r/e/i/reinasex/KaYa-Huang-Atago-Race-Queen-17s.jpg"
      ],
      "url": "https://reinasex.blog.2nt.com/blog-entry-1772.html",
      "source": "reinasex"
    },
    {
      "name": "Hidori Rose（@Hidori_Rose）さん - きれいなお姉さん無修正",
      "id": "hidori_rose",
      "insta": "https://www.instagram.com/hidori_rose/",
      "images": [
        "https://x8.shinobi.jp/bin/ll?100057901",
        "https://blog-imgs-145-origin.2nt.com/r/e/i/reinasex/HidoriRose-Shinano-02s.jpg",
        "https://blog-imgs-145-origin.2nt.com/r/e/i/reinasex/HidoriRose-Shinano-06s.jpg"
      ],
      "url": "https://reinasex.blog.2nt.com/blog-entry-1756.html",
      "source": "reinasex"
    },
    {
      "name": "赤西夜夜（@vddsd210796）さん - きれいなお姉さん無修正",
      "id": "vddsd210796",
      "insta": "",
      "images": [
        "https://x8.shinobi.jp/bin/ll?100057901",
        "https://blog-imgs-145-origin.2nt.com/r/e/i/reinasex/vddsd210796-Sister-01s.jpg",
        "https://blog-imgs-145-origin.2nt.com/r/e/i/reinasex/vddsd210796-Sister-07s.jpg"
      ],
      "url": "https://reinasex.blog.2nt.com/blog-entry-1755.html",
      "source": "reinasex"
    },
    {
      "name": "Koy Kyoko（@koykyoko1）さん - きれいなお姉さん無修正",
      "id": "koykyoko1",
      "insta": "https://www.instagram.com/koykyoko1",
      "images": [
        "https://x8.shinobi.jp/bin/ll?100057901",
        "https://blog-imgs-145-origin.2nt.com/r/e/i/reinasex/Kyokoyaki-Fern-04s.jpg",
        "https://blog-imgs-145-origin.2nt.com/r/e/i/reinasex/Kyokoyaki-Fern-05s.jpg"
      ],
      "url": "https://reinasex.blog.2nt.com/blog-entry-1593.html",
      "source": "reinasex"
    },
    {
      "name": "毛毛喵（@H_momocat）さん - きれいなお姉さん無修正",
      "id": "H_momocat",
      "insta": "https://www.instagram.com/mokit728/",
      "images": [
        "https://x8.shinobi.jp/bin/ll?100057901",
        "https://blog-imgs-145-origin.2nt.com/r/e/i/reinasex/Momocat-JK-Train-002s.jpg",
        "https://blog-imgs-145-origin.2nt.com/r/e/i/reinasex/Momocat-JK-Train-006s.jpg"
      ],
      "url": "https://reinasex.blog.2nt.com/blog-entry-1727.html",
      "source": "reinasex"
    },
    {
      "name": "魔法少女♡瀴瀴（@mahoushoujo1222）さん - きれいなお姉さん無修正",
      "id": "mahoushoujo1222",
      "insta": "https://www.instagram.com/cherry.cupido.kuriimu/",
      "images": [
        "https://x8.shinobi.jp/bin/ll?100057901",
        "https://blog-imgs-145-origin.2nt.com/r/e/i/reinasex/mahoushoujo-bondage-01s.jpg",
        "https://blog-imgs-145-origin.2nt.com/r/e/i/reinasex/mahoushoujo-bondage-02s.jpg"
      ],
      "url": "https://reinasex.blog.2nt.com/blog-entry-1676.html",
      "source": "reinasex"
    },
    {
      "name": "Yuumeilyn- 玲兒（@yuumeilyn）さん - きれいなお姉さん無修正",
      "id": "yuumeilyn",
      "insta": "https://www.instagram.com/yuu.meilyn/",
      "images": [
        "https://x8.shinobi.jp/bin/ll?100057901",
        "https://blog-imgs-145-origin.2nt.com/r/e/i/reinasex/Yuumeilyn-Nahida-01s.jpg",
        "https://blog-imgs-145-origin.2nt.com/r/e/i/reinasex/Yuumeilyn-Nahida-02s.jpg"
      ],
      "url": "https://reinasex.blog.2nt.com/blog-entry-1714.html",
      "source": "reinasex"
    },
    {
      "name": "Machi馬吉💎（@_Machi0910）さん - きれいなお姉さん無修正",
      "id": "0910Machi",
      "insta": "https://www.instagram.com/m._.achi/",
      "images": [
        "https://x8.shinobi.jp/bin/ll?100057901",
        "https://blog-imgs-145-origin.2nt.com/r/e/i/reinasex/Machi-Honkai-Castrice-011s.jpg",
        "https://blog-imgs-145-origin.2nt.com/r/e/i/reinasex/Machi-Honkai-Castrice-027s.jpg"
      ],
      "url": "https://reinasex.blog.2nt.com/blog-entry-1737.html",
      "source": "reinasex"
    },
    {
      "name": "沖田凛花Rinkaさん（@okitarinka_01） - きれいなお姉さん無修正",
      "id": "okitarinka_01",
      "insta": "",
      "images": [
        "https://x8.shinobi.jp/bin/ll?100057901",
        "https://blog-imgs-145-origin.2nt.com/r/e/i/reinasex/Okita-Rinka-BunnyMaide-01s.jpg",
        "https://blog-imgs-145-origin.2nt.com/r/e/i/reinasex/Okita-Rinka-BunnyMaide-06s.jpg"
      ],
      "url": "https://reinasex.blog.2nt.com/blog-entry-1564.html",
      "source": "reinasex"
    },
    {
      "name": "小礼好困さん（@SleeppyLee1） - きれいなお姉さん無修正",
      "id": "sleeppylee1",
      "insta": "",
      "images": [
        "https://x8.shinobi.jp/bin/ll?100057901",
        "https://blog-imgs-145-origin.2nt.com/r/e/i/reinasex/SleeppyLee1-Mashu-11s.jpg",
        "https://blog-imgs-145-origin.2nt.com/r/e/i/reinasex/SleeppyLee1-Mashu-20s.jpg"
      ],
      "url": "https://reinasex.blog.2nt.com/blog-entry-1713.html",
      "source": "reinasex"
    },
    {
      "name": "花音栗子（@Chestnugirl）さん - きれいなお姉さん無修正",
      "id": "Chestnugirl",
      "insta": "",
      "images": [
        "https://x8.shinobi.jp/bin/ll?100057901",
        "https://blog-imgs-145-origin.2nt.com/r/e/i/reinasex/Chestnugirl-Peach-01s.jpg",
        "https://blog-imgs-145-origin.2nt.com/r/e/i/reinasex/Chestnugirl-Peach-08s.jpg"
      ],
      "url": "https://reinasex.blog.2nt.com/blog-entry-1712.html",
      "source": "reinasex"
    },
    {
      "name": "Mewjiic（@lMusiclz）さん - きれいなお姉さん無修正",
      "id": "lMusiclz",
      "insta": "https://www.instagram.com/mewjiic_cos/",
      "images": [
        "https://x8.shinobi.jp/bin/ll?100057901",
        "https://blog-imgs-145-origin.2nt.com/r/e/i/reinasex/Mewjiic-AsumaToki-01s.jpg",
        "https://blog-imgs-145-origin.2nt.com/r/e/i/reinasex/Mewjiic-AsumaToki-07s.jpg"
      ],
      "url": "https://reinasex.blog.2nt.com/blog-entry-1689.html",
      "source": "reinasex"
    },
    {
      "name": "爆机少女喵小吉（@RGM79_Pilot）さん - きれいなお姉さん無修正",
      "id": "nekokoyoshi_",
      "insta": "",
      "images": [
        "https://x8.shinobi.jp/bin/ll?100057901",
        "https://blog-imgs-145-origin.2nt.com/r/e/i/reinasex/NekoKoyoshi-Inori-02s.jpg",
        "https://blog-imgs-145-origin.2nt.com/r/e/i/reinasex/NekoKoyoshi-Inori-03s.jpg"
      ],
      "url": "https://reinasex.blog.2nt.com/blog-entry-1688.html",
      "source": "reinasex"
    },
    {
      "name": "浵卡Tokar🔞（@laurus0711）さん - きれいなお姉さん無修正",
      "id": "laurus0711",
      "insta": "https://www.instagram.com/_minncoco/",
      "images": [
        "https://x8.shinobi.jp/bin/ll?100057901",
        "https://blog-imgs-145-origin.2nt.com/r/e/i/reinasex/Tokar-Furina-01.jpg",
        "https://blog-imgs-145-origin.2nt.com/r/e/i/reinasex/Tokar-Furina-03.jpg"
      ],
      "url": "https://reinasex.blog.2nt.com/blog-entry-1687.html",
      "source": "reinasex"
    },
    {
      "name": "小欣奈（@lovewxnn）さん - きれいなお姉さん無修正",
      "id": "lovewxnn",
      "insta": "",
      "images": [
        "https://x8.shinobi.jp/bin/ll?100057901",
        "https://blog-imgs-145-origin.2nt.com/r/e/i/reinasex/lovewxnn-Nahida-01s.jpg",
        "https://blog-imgs-145-origin.2nt.com/r/e/i/reinasex/lovewxnn-Nahida-40s.jpg"
      ],
      "url": "https://reinasex.blog.2nt.com/blog-entry-1595.html",
      "source": "reinasex"
    },
    {
      "name": "核酸酱（@Asai_chan_）さん - きれいなお姉さん無修正",
      "id": "asai_chan_",
      "insta": "",
      "images": [
        "https://x8.shinobi.jp/bin/ll?100057901",
        "https://blog-imgs-145-origin.2nt.com/r/e/i/reinasex/AsaiChan-ShangXinCi-01s.jpg",
        "https://blog-imgs-145-origin.2nt.com/r/e/i/reinasex/AsaiChan-ShangXinCi-02s.jpg"
      ],
      "url": "https://reinasex.blog.2nt.com/blog-entry-1678.html",
      "source": "reinasex"
    },
    {
      "name": "魔法少女♡瀴瀴（@mahoushoujo1222）さん - きれいなお姉さん無修正",
      "id": "mahoushoujo1222",
      "insta": "https://www.instagram.com/cherry.cupido.kuriimu/",
      "images": [
        "https://x8.shinobi.jp/bin/ll?100057901",
        "https://blog-imgs-145-origin.2nt.com/r/e/i/reinasex/mahoushoujo-yaemiko-01s.jpg",
        "https://blog-imgs-145-origin.2nt.com/r/e/i/reinasex/mahoushoujo-yaemiko-02s.jpg"
      ],
      "url": "https://reinasex.blog.2nt.com/blog-entry-1602.html",
      "source": "reinasex"
    },
    {
      "name": "KaYa Huang（萱）（@kaya1028）さん - きれいなお姉さん無修正",
      "id": "Kayaaa1028",
      "insta": "https://www.instagram.com/kaya_huang/?hl=ja",
      "images": [
        "https://x8.shinobi.jp/bin/ll?100057901",
        "https://blog-imgs-145-origin.2nt.com/r/e/i/reinasex/KaYa-Huang-Asuma-Toki-Bunny-Suit-1s.jpg",
        "https://blog-imgs-145-origin.2nt.com/r/e/i/reinasex/KaYa-Huang-Asuma-Toki-Bunny-Suit-10s.jpg"
      ],
      "url": "https://reinasex.blog.2nt.com/blog-entry-1673.html",
      "source": "reinasex"
    },
    {
      "name": "Koy Kyoko（@koykyoko1）さん - きれいなお姉さん無修正",
      "id": "koykyoko1",
      "insta": "https://www.instagram.com/koykyoko1",
      "images": [
        "https://x8.shinobi.jp/bin/ll?100057901",
        "https://blog-imgs-145-origin.2nt.com/r/e/i/reinasex/Kyokoyaki-2B-01xs.jpg",
        "https://blog-imgs-145-origin.2nt.com/r/e/i/reinasex/Kyokoyaki-2B-04xs.jpg"
      ],
      "url": "https://reinasex.blog.2nt.com/blog-entry-1659.html",
      "source": "reinasex"
    },
    {
      "name": "Kitty Kumさん（@kittyxkum） - きれいなお姉さん無修正",
      "id": "kittyxkum",
      "insta": "https://www.instagram.com/kittykumx/",
      "images": [
        "https://x8.shinobi.jp/bin/ll?100057901",
        "https://blog-imgs-145-origin.2nt.com/r/e/i/reinasex/KittyxKum-YorForger-033s.jpg",
        "https://blog-imgs-145-origin.2nt.com/r/e/i/reinasex/KittyxKum-YorForger-038s.jpg"
      ],
      "url": "https://reinasex.blog.2nt.com/blog-entry-1653.html",
      "source": "reinasex"
    },
    {
      "name": "Arty huang（@huang_arty）さん - きれいなお姉さん無修正",
      "id": "Artydailylife",
      "insta": "",
      "images": [
        "https://x8.shinobi.jp/bin/ll?100057901",
        "https://blog-imgs-145-origin.2nt.com/r/e/i/reinasex/Arty-Huang-Chinese-New-Year-2023-01s.jpg",
        "https://blog-imgs-145-origin.2nt.com/r/e/i/reinasex/Arty-Huang-Chinese-New-Year-2023-02s.jpg"
      ],
      "url": "https://reinasex.blog.2nt.com/blog-entry-1638.html",
      "source": "reinasex"
    },
    {
      "name": "Minichu（@LiceMini）さん - きれいなお姉さん無修正",
      "id": "LiceMini",
      "insta": "",
      "images": [
        "https://x8.shinobi.jp/bin/ll?100057901",
        "https://blog-imgs-145-origin.2nt.com/r/e/i/reinasex/Minichu-Eula-1s.jpg",
        "https://blog-imgs-145-origin.2nt.com/r/e/i/reinasex/Minichu-Eula-11s.jpg"
      ],
      "url": "https://reinasex.blog.2nt.com/blog-entry-1637.html",
      "source": "reinasex"
    },
    {
      "name": "桃暖酱🍑（@taonuanjiang521）さん - きれいなお姉さん無修正",
      "id": "taonuanjiang521",
      "insta": "",
      "images": [
        "https://x8.shinobi.jp/bin/ll?100057901",
        "https://blog-imgs-145-origin.2nt.com/r/e/i/reinasex/taonuanjiang521-Wedding-01s.jpg",
        "https://blog-imgs-145-origin.2nt.com/r/e/i/reinasex/taonuanjiang521-Wedding-09s.jpg"
      ],
      "url": "https://reinasex.blog.2nt.com/blog-entry-1612.html",
      "source": "reinasex"
    },
    {
      "name": "Potato Godzilla - 可愛い怪獣 🌻（@potato2307）さん - きれいなお姉さん無修正",
      "id": "potato2307",
      "insta": "https://www.instagram.com/potatogodzilla_reallife/",
      "images": [
        "https://x8.shinobi.jp/bin/ll?100057901",
        "https://blog-imgs-145-origin.2nt.com/r/e/i/reinasex/Potato-Godzilla-Hatsune-Miku-Xmas-01s.jpg",
        "https://blog-imgs-145-origin.2nt.com/r/e/i/reinasex/Potato-Godzilla-Hatsune-Miku-Xmas-02s.jpg"
      ],
      "url": "https://reinasex.blog.2nt.com/blog-entry-1632.html",
      "source": "reinasex"
    },
    {
      "name": "毛毛喵（@H_momocat）さん - きれいなお姉さん無修正",
      "id": "H_momocat",
      "insta": "https://www.instagram.com/mokit728/",
      "images": [
        "https://x8.shinobi.jp/bin/ll?100057901",
        "https://blog-imgs-145-origin.2nt.com/r/e/i/reinasex/Momocat-Shorekeeper-01xs.jpg",
        "https://blog-imgs-145-origin.2nt.com/r/e/i/reinasex/Momocat-Shorekeeper-04xs.jpg"
      ],
      "url": "https://reinasex.blog.2nt.com/blog-entry-1614.html",
      "source": "reinasex"
    },
    {
      "name": "Yuumeilyn- 玲兒（@yuumeilyn）さん - きれいなお姉さん無修正",
      "id": "yuumeilyn",
      "insta": "https://www.instagram.com/yuu.meilyn/",
      "images": [
        "https://x8.shinobi.jp/bin/ll?100057901",
        "https://blog-imgs-145-origin.2nt.com/r/e/i/reinasex/Yuumeilyn-AniGrok-01s.jpg",
        "https://blog-imgs-145-origin.2nt.com/r/e/i/reinasex/Yuumeilyn-AniGrok-09s.jpg"
      ],
      "url": "https://reinasex.blog.2nt.com/blog-entry-1613.html",
      "source": "reinasex"
    },
    {
      "name": "絞肉姬Walküre🏴‍☠️（@SuccAbyss）さん - きれいなお姉さん無修正",
      "id": "NWalkure",
      "insta": "https://www.instagram.com/thevalkyrie_666",
      "images": [
        "https://x8.shinobi.jp/bin/ll?100057901",
        "https://blog-imgs-145-origin.2nt.com/r/e/i/reinasex/Walkure-Asuka-Swim-01s.jpg",
        "https://blog-imgs-145-origin.2nt.com/r/e/i/reinasex/Walkure-Asuka-Swim-06s.jpg"
      ],
      "url": "https://reinasex.blog.2nt.com/blog-entry-1619.html",
      "source": "reinasex"
    },
    {
      "name": "Aokochan あおこちゃん - きれいなお姉さん無修正",
      "id": "aokotan1",
      "insta": "https://www.instagram.com/aokosuu/",
      "images": [
        "https://x8.shinobi.jp/bin/ll?100057901",
        "https://blog-imgs-145-origin.2nt.com/r/e/i/reinasex/Aokotan-Rem-00s.jpg",
        "https://blog-imgs-145-origin.2nt.com/r/e/i/reinasex/Aokotan-Rem-01s.jpg"
      ],
      "url": "https://reinasex.blog.2nt.com/blog-entry-1611.html",
      "source": "reinasex"
    },
    {
      "name": "浵卡Tokar🔞（@laurus0711）さん - きれいなお姉さん無修正",
      "id": "laurus0711",
      "insta": "https://www.instagram.com/_minncoco/",
      "images": [
        "https://x8.shinobi.jp/bin/ll?100057901",
        "https://blog-imgs-145-origin.2nt.com/r/e/i/reinasex/Tokar-2B-Bride-01s.jpg",
        "https://blog-imgs-145-origin.2nt.com/r/e/i/reinasex/Tokar-2B-Bride-02s.jpg"
      ],
      "url": "https://reinasex.blog.2nt.com/blog-entry-1603.html",
      "source": "reinasex"
    },
    {
      "name": "魔法少女♡瀴瀴（@mahoushoujo1222）さん - きれいなお姉さん無修正",
      "id": "mahoushoujo1222",
      "insta": "https://www.instagram.com/cherry.cupido.kuriimu/",
      "images": [
        "https://x8.shinobi.jp/bin/ll?100057901",
        "https://blog-imgs-145-origin.2nt.com/r/e/i/reinasex/mahoushoujo-shutendouji-01s.jpg",
        "https://blog-imgs-145-origin.2nt.com/r/e/i/reinasex/mahoushoujo-shutendouji-03s.jpg"
      ],
      "url": "https://reinasex.blog.2nt.com/blog-entry-1596.html",
      "source": "reinasex"
    },
    {
      "name": "小欣奈（@lovewxnn）さん - きれいなお姉さん無修正",
      "id": "lovewxnn",
      "insta": "",
      "images": [
        "https://x8.shinobi.jp/bin/ll?100057901",
        "https://blog-imgs-145-origin.2nt.com/r/e/i/reinasex/lovewxnn-Kinako-01s.jpg",
        "https://blog-imgs-145-origin.2nt.com/r/e/i/reinasex/lovewxnn-Kinako-02s.jpg"
      ],
      "url": "https://reinasex.blog.2nt.com/blog-entry-1594.html",
      "source": "reinasex"
    },
    {
      "name": "Koy Kyoko（@koykyoko1）さん - きれいなお姉さん無修正",
      "id": "koykyoko1",
      "insta": "https://www.instagram.com/koykyoko1",
      "images": [
        "https://x8.shinobi.jp/bin/ll?100057901",
        "https://blog-imgs-145-origin.2nt.com/r/e/i/reinasex/Kyokoyaki-Miku-102s.jpg",
        "https://blog-imgs-145-origin.2nt.com/r/e/i/reinasex/Kyokoyaki-Miku-103s.jpg"
      ],
      "url": "https://reinasex.blog.2nt.com/blog-entry-1592.html",
      "source": "reinasex"
    },
    {
      "name": "桜夜まよいさん（あおいみつりさん） - きれいなお姉さん無修正",
      "id": "MitsuriAoi",
      "insta": "",
      "images": [
        "https://x8.shinobi.jp/bin/ll?100057901",
        "https://blog-imgs-145-origin.2nt.com/r/e/i/reinasex/gachinco-satoko-1-7s.jpg",
        "https://blog-imgs-145-origin.2nt.com/r/e/i/reinasex/gachinco-satoko-2-8s.jpg"
      ],
      "url": "https://reinasex.blog.2nt.com/blog-entry-1273.html",
      "source": "reinasex"
    },
    {
      "name": "赤西夜夜（@vddsd210796）さん - きれいなお姉さん無修正",
      "id": "vddsd210796",
      "insta": "",
      "images": [
        "https://x8.shinobi.jp/bin/ll?100057901",
        "https://blog-imgs-145-origin.2nt.com/r/e/i/reinasex/ChiXiYeYe-Hatsune-065s.jpg",
        "https://blog-imgs-145-origin.2nt.com/r/e/i/reinasex/ChiXiYeYe-Hatsune-066s.jpg"
      ],
      "url": "https://reinasex.blog.2nt.com/blog-entry-1581.html",
      "source": "reinasex"
    },
    {
      "name": "胡桃璃愛さん - きれいなお姉さん無修正",
      "id": "usatumilk_oO",
      "insta": "https://www.instagram.com/millk_pyon",
      "images": [
        "https://x8.shinobi.jp/bin/ll?100057901",
        "https://blog-imgs-145-origin.2nt.com/r/e/i/reinasex/Cospuri-RiaKurumi-0512-01s.jpg",
        "https://blog-imgs-145-origin.2nt.com/r/e/i/reinasex/Cospuri-RiaKurumi-0509-01s.jpg"
      ],
      "url": "https://reinasex.blog.2nt.com/blog-entry-909.html",
      "source": "reinasex"
    },
    {
      "name": "Hidori Rose（@Hidori_Rose）さん - きれいなお姉さん無修正",
      "id": "hidori_rose",
      "insta": "https://www.instagram.com/hidori_rose/",
      "images": [
        "https://x8.shinobi.jp/bin/ll?100057901",
        "https://blog-imgs-145-origin.2nt.com/r/e/i/reinasex/Hidori-Rose-Grok-Ani-2s.jpg",
        "https://blog-imgs-145-origin.2nt.com/r/e/i/reinasex/Hidori-Rose-Grok-Ani-5s.jpg"
      ],
      "url": "https://reinasex.blog.2nt.com/blog-entry-1582.html",
      "source": "reinasex"
    },
    {
      "name": "橙子喵酱（@chengzimiaoj）さん - きれいなお姉さん無修正",
      "id": "chengzimiaoj",
      "insta": "",
      "images": [
        "https://x8.shinobi.jp/bin/ll?100057901",
        "https://blog-imgs-145-origin.2nt.com/r/e/i/reinasex/Chengzimiaoj-Taihou-04xs.jpg",
        "https://blog-imgs-145-origin.2nt.com/r/e/i/reinasex/Chengzimiaoj-Taihou-01s.jpg"
      ],
      "url": "https://reinasex.blog.2nt.com/blog-entry-1568.html",
      "source": "reinasex"
    },
    {
      "name": "毛毛喵（@H_momocat）さん - きれいなお姉さん無修正",
      "id": "H_momocat",
      "insta": "https://www.instagram.com/mokit728/",
      "images": [
        "https://x8.shinobi.jp/bin/ll?100057901",
        "https://blog-imgs-145-origin.2nt.com/r/e/i/reinasex/momocat-furina-01s.jpg",
        "https://blog-imgs-145-origin.2nt.com/r/e/i/reinasex/momocat-furina-10s.jpg"
      ],
      "url": "https://reinasex.blog.2nt.com/blog-entry-1569.html",
      "source": "reinasex"
    },
    {
      "name": "沖田凛花Rinkaさん（@okitarinka_01） - きれいなお姉さん無修正",
      "id": "okitarinka_01",
      "insta": "",
      "images": [
        "https://x8.shinobi.jp/bin/ll?100057901",
        "https://blog-imgs-145-origin.2nt.com/r/e/i/reinasex/Okita-Rinka-Bride-01s.jpg",
        "https://blog-imgs-145-origin.2nt.com/r/e/i/reinasex/Okita-Rinka-Bride-02s.jpg"
      ],
      "url": "https://reinasex.blog.2nt.com/blog-entry-1563.html",
      "source": "reinasex"
    },
    {
      "name": "爆机少女喵小吉（@RGM79_Pilot）さん - きれいなお姉さん無修正",
      "id": "nekokoyoshi_",
      "insta": "",
      "images": [
        "https://x8.shinobi.jp/bin/ll?100057901",
        "https://blog-imgs-145-origin.2nt.com/r/e/i/reinasex/NekoKoyoshi-Taihou-02s.jpg",
        "https://blog-imgs-145-origin.2nt.com/r/e/i/reinasex/NekoKoyoshi-Taihou-03s.jpg"
      ],
      "url": "https://reinasex.blog.2nt.com/blog-entry-1553.html",
      "source": "reinasex"
    },
    {
      "name": "Yuumeilyn- 玲兒（@yuumeilyn）さん - きれいなお姉さん無修正",
      "id": "yuumeilyn",
      "insta": "https://www.instagram.com/yuu.meilyn/",
      "images": [
        "https://x8.shinobi.jp/bin/ll?100057901",
        "https://blog-imgs-145-origin.2nt.com/r/e/i/reinasex/Yuumeilyn-Fern-Sousou-no-Frieren-1s.jpg",
        "https://blog-imgs-145-origin.2nt.com/r/e/i/reinasex/Yuumeilyn-Fern-Sousou-no-Frieren-7s.jpg"
      ],
      "url": "https://reinasex.blog.2nt.com/blog-entry-1552.html",
      "source": "reinasex"
    },
    {
      "name": "浵卡Tokar🔞（@laurus0711）さん - きれいなお姉さん無修正",
      "id": "laurus0711",
      "insta": "https://www.instagram.com/_minncoco/",
      "images": [
        "https://x8.shinobi.jp/bin/ll?100057901",
        "https://blog-imgs-145-origin.2nt.com/r/e/i/reinasex/Tokar-Baltimore-01s.jpg",
        "https://blog-imgs-145-origin.2nt.com/r/e/i/reinasex/Tokar-Baltimore-02s.jpg"
      ],
      "url": "https://reinasex.blog.2nt.com/blog-entry-1546.html",
      "source": "reinasex"
    },
    {
      "name": "落落Raku_66🐾（@rakuraku166）さん - きれいなお姉さん無修正",
      "id": "rakuraku166",
      "insta": "https://www.instagram.com/rakuroneko_66/",
      "images": [
        "https://x8.shinobi.jp/bin/ll?100057901",
        "https://blog-imgs-145-origin.2nt.com/r/e/i/reinasex/Rakuraku-Live-01xs.jpg",
        "https://blog-imgs-145-origin.2nt.com/r/e/i/reinasex/Rakuraku-Live-08s.jpg"
      ],
      "url": "https://reinasex.blog.2nt.com/blog-entry-1541.html",
      "source": "reinasex"
    },
    {
      "name": "Arty huang（@huang_arty）さん - きれいなお姉さん無修正",
      "id": "Artydailylife",
      "insta": "",
      "images": [
        "https://x8.shinobi.jp/bin/ll?100057901",
        "https://blog-imgs-145-origin.2nt.com/r/e/i/reinasex/Arty-Huang-Asuma-Toki-Bunny-Suit-1s.jpg",
        "https://blog-imgs-145-origin.2nt.com/r/e/i/reinasex/Arty-Huang-Asuma-Toki-Bunny-Suit-6s.jpg"
      ],
      "url": "https://reinasex.blog.2nt.com/blog-entry-1540.html",
      "source": "reinasex"
    },
    {
      "name": "Minichu（@LiceMini）さん - きれいなお姉さん無修正",
      "id": "LiceMini",
      "insta": "",
      "images": [
        "https://x8.shinobi.jp/bin/ll?100057901",
        "https://blog-imgs-145-origin.2nt.com/r/e/i/reinasex/Minichu-2B-Latex-Nun-6xs.jpg",
        "https://blog-imgs-145-origin.2nt.com/r/e/i/reinasex/Minichu-2B-Latex-Nun-1s.jpg"
      ],
      "url": "https://reinasex.blog.2nt.com/blog-entry-1524.html",
      "source": "reinasex"
    },
    {
      "name": "小丁こまち🌹🔞さん（@_KOMACHI_1） - きれいなお姉さん無修正",
      "id": "_KOMACHI_2",
      "insta": "https://www.instagram.com/_komachi_1/?hl=ja",
      "images": [
        "https://x8.shinobi.jp/bin/ll?100057901",
        "https://blog-imgs-145-origin.2nt.com/r/e/i/reinasex/Fantasy-Factory-Oil-01s.jpg",
        "https://blog-imgs-145-origin.2nt.com/r/e/i/reinasex/Fantasy-Factory-Oil-02s.jpg"
      ],
      "url": "https://reinasex.blog.2nt.com/blog-entry-1523.html",
      "source": "reinasex"
    },
    {
      "name": "RikaChan ʕ•ᴥ•ʔ（@RikaChan2746）さん - きれいなお姉さん無修正",
      "id": "rikachan2746",
      "insta": "https://www.instagram.com/sansan_dnc/",
      "images": [
        "https://x8.shinobi.jp/bin/ll?100057901",
        "https://blog-imgs-145-origin.2nt.com/r/e/i/reinasex/RikaChan-YaeMiko-01s.jpg",
        "https://blog-imgs-145-origin.2nt.com/r/e/i/reinasex/RikaChan-YaeMiko-14xs.jpg"
      ],
      "url": "https://reinasex.blog.2nt.com/blog-entry-1522.html",
      "source": "reinasex"
    },
    {
      "name": "核酸酱（@Asai_chan_）さん - きれいなお姉さん無修正",
      "id": "asai_chan_",
      "insta": "",
      "images": [
        "https://x8.shinobi.jp/bin/ll?100057901",
        "https://blog-imgs-145-origin.2nt.com/r/e/i/reinasex/Asai-Chan-01xs.jpg",
        "https://blog-imgs-145-origin.2nt.com/r/e/i/reinasex/Asai-Chan-05s.jpg"
      ],
      "url": "https://reinasex.blog.2nt.com/blog-entry-1512.html",
      "source": "reinasex"
    },
    {
      "name": "VirtualGeisha（@VirtualGeishaaa）さん - きれいなお姉さん無修正",
      "id": "VirtualGeishaaa",
      "insta": "https://www.instagram.com/thevirtualgeisha/",
      "images": [
        "https://x8.shinobi.jp/bin/ll?100057901",
        "https://blog-imgs-145-origin.2nt.com/r/e/i/reinasex/Virtual-Geisha-Tifa-01s.jpg",
        "https://blog-imgs-145-origin.2nt.com/r/e/i/reinasex/Virtual-Geisha-Tifa-25s.jpg"
      ],
      "url": "https://reinasex.blog.2nt.com/blog-entry-1497.html",
      "source": "reinasex"
    },
    {
      "name": "桃暖酱🍑（@taonuanjiang521）さん - きれいなお姉さん無修正",
      "id": "taonuanjiang521",
      "insta": "",
      "images": [
        "https://x8.shinobi.jp/bin/ll?100057901",
        "https://blog-imgs-501-origin.2nt.com/c/u/t/cutiepussy1/taonuanjiang521-Jouga-01s.jpg",
        "https://blog-imgs-145-origin.2nt.com/r/e/i/reinasex/taonuanjiang521-Jouga-10s.jpg"
      ],
      "url": "https://reinasex.blog.2nt.com/blog-entry-1496.html",
      "source": "reinasex"
    },
    {
      "name": "Aokochan あおこちゃん - きれいなお姉さん無修正",
      "id": "aokotan1",
      "insta": "https://www.instagram.com/aokosuu/",
      "images": [
        "https://x8.shinobi.jp/bin/ll?100057901",
        "https://blog-imgs-145-origin.2nt.com/r/e/i/reinasex/Aokochan-Marin-Succubus-02s.jpg",
        "https://blog-imgs-145-origin.2nt.com/r/e/i/reinasex/Aokochan-Marin-Succubus-12s.jpg"
      ],
      "url": "https://reinasex.blog.2nt.com/blog-entry-1477.html",
      "source": "reinasex"
    },
    {
      "name": "毛毛喵（@H_momocat）さん - きれいなお姉さん無修正",
      "id": "H_momocat",
      "insta": "https://www.instagram.com/mokit728/",
      "images": [
        "https://x8.shinobi.jp/bin/ll?100057901",
        "https://blog-imgs-145-origin.2nt.com/r/e/i/reinasex/momocat-2b-01s.jpg",
        "https://blog-imgs-145-origin.2nt.com/r/e/i/reinasex/momocat-2b-04s.jpg"
      ],
      "url": "https://reinasex.blog.2nt.com/blog-entry-1476.html",
      "source": "reinasex"
    },
    {
      "name": "Hidori Rose（@Hidori_Rose）さん - きれいなお姉さん無修正",
      "id": "hidori_rose",
      "insta": "https://www.instagram.com/hidori_rose/",
      "images": [
        "https://x8.shinobi.jp/bin/ll?100057901",
        "https://blog-imgs-145-origin.2nt.com/r/e/i/reinasex/HidoriRose-YorForger-15s.jpg",
        "https://blog-imgs-145-origin.2nt.com/r/e/i/reinasex/HidoriRose-YorForger-16s.jpg"
      ],
      "url": "https://reinasex.blog.2nt.com/blog-entry-1469.html",
      "source": "reinasex"
    },
    {
      "name": "浵卡Tokar🔞（@laurus0711）さん - きれいなお姉さん無修正",
      "id": "laurus0711",
      "insta": "https://www.instagram.com/_minncoco/",
      "images": [
        "https://x8.shinobi.jp/bin/ll?100057901",
        "https://blog-imgs-145-origin.2nt.com/r/e/i/reinasex/Tokar-AsumaToki-01s.jpg",
        "https://blog-imgs-145-origin.2nt.com/r/e/i/reinasex/Tokar-AsumaToki-04s.jpg"
      ],
      "url": "https://reinasex.blog.2nt.com/blog-entry-1468.html",
      "source": "reinasex"
    },
    {
      "name": "花音栗子（@Chestnugirl）さん - きれいなお姉さん無修正",
      "id": "Chestnugirl",
      "insta": "",
      "images": [
        "https://x8.shinobi.jp/bin/ll?100057901",
        "https://blog-imgs-145-origin.2nt.com/r/e/i/reinasex/Chestnugirl-GymUniform-01s.jpg",
        "https://blog-imgs-145-origin.2nt.com/r/e/i/reinasex/Chestnugirl-GymUniform-11s.jpg"
      ],
      "url": "https://reinasex.blog.2nt.com/blog-entry-1451.html",
      "source": "reinasex"
    },
    {
      "name": "赤西夜夜（@vddsd210796）さん - きれいなお姉さん無修正",
      "id": "vddsd210796",
      "insta": "",
      "images": [
        "https://x8.shinobi.jp/bin/ll?100057901",
        "https://blog-imgs-145-origin.2nt.com/r/e/i/reinasex/ChiXiYeYe-Hatsune-005s.jpg",
        "https://blog-imgs-145-origin.2nt.com/r/e/i/reinasex/ChiXiYeYe-Hatsune-015s.jpg"
      ],
      "url": "https://reinasex.blog.2nt.com/blog-entry-1428.html",
      "source": "reinasex"
    },
    {
      "name": "Kitty Kumさん（@kittyxkum） - きれいなお姉さん無修正",
      "id": "kittyxkum",
      "insta": "https://www.instagram.com/kittykumx/",
      "images": [
        "https://x8.shinobi.jp/bin/ll?100057901",
        "https://blog-imgs-145-origin.2nt.com/r/e/i/reinasex/kittyxkum-Vanilla-001s.jpg",
        "https://blog-imgs-145-origin.2nt.com/r/e/i/reinasex/kittyxkum-Vanilla-005s.jpg"
      ],
      "url": "https://reinasex.blog.2nt.com/blog-entry-1450.html",
      "source": "reinasex"
    },
    {
      "name": "Reina O'Hara(@reinaohara_1030)さん - きれいなお姉さん無修正",
      "id": "reinaohara_1030",
      "insta": "https://www.instagram.com/reinaohara2025/",
      "images": [
        "https://x8.shinobi.jp/bin/ll?100057901",
        "https://blog-imgs-145-origin.2nt.com/r/e/i/reinasex/Reina-iStripper-Oiled-01s.jpg",
        "https://blog-imgs-145-origin.2nt.com/r/e/i/reinasex/Reina-iStripper-Oiled-02s.jpg"
      ],
      "url": "https://reinasex.blog.2nt.com/blog-entry-1796.html",
      "source": "reinasex"
    },
    {
      "name": "弘中れおなさんと本多まいさん - きれいなお姉さん無修正",
      "id": "hirose_riona",
      "insta": "https://www.instagram.com/hirose_riona1210/",
      "images": [
        "https://x8.shinobi.jp/bin/ll?100057901",
        "https://blog-imgs-145-origin.2nt.com/r/e/i/reinasex/123125-001.jpg",
        "https://blog-imgs-145-origin.2nt.com/r/e/i/reinasex/123125-001-013s.jpg"
      ],
      "url": "https://reinasex.blog.2nt.com/blog-entry-1747.html",
      "source": "reinasex"
    },
    {
      "name": "柊麗奈さん（@kimisapu_love） - きれいなお姉さん無修正",
      "id": "kimisapu_love",
      "insta": "",
      "images": [
        "https://x8.shinobi.jp/bin/ll?100057901",
        "https://blog-imgs-145-origin.2nt.com/r/e/i/reinasex/081421_001.jpg",
        "https://jjgirls.com/uncensored/1pondo/reina-hiiragi/081421_001/reina-hiiragi-1.jpg"
      ],
      "url": "https://reinasex.blog.2nt.com/blog-entry-1783.html",
      "source": "reinasex"
    },
    {
      "name": "小川桃果さんと藤野りんさん - きれいなお姉さん無修正",
      "id": "tenshinhan0327",
      "insta": "",
      "images": [
        "https://x8.shinobi.jp/bin/ll?100057901",
        "https://blog-imgs-145-origin.2nt.com/r/e/i/reinasex/010426-001s.jpg",
        "https://jjgirls.com/uncensored/caribbeancom/rin-fujino-momoka-ogawa/010426-001/rin-fujino-momoka-ogawa-1.jpg"
      ],
      "url": "https://reinasex.blog.2nt.com/blog-entry-1781.html",
      "source": "reinasex"
    },
    {
      "name": "佐倉みこさん（桜もこさん） - きれいなお姉さん無修正",
      "id": "moko_sakura3",
      "insta": "https://www.instagram.com/mokochan319/",
      "images": [
        "https://x8.shinobi.jp/bin/ll?100057901",
        "https://blog-imgs-145-origin.2nt.com/r/e/i/reinasex/heyzo-3811.jpg",
        "https://jjgirls.com/uncensored/heyzo/miko-sakura/3811/miko-sakura-2.jpg"
      ],
      "url": "https://reinasex.blog.2nt.com/blog-entry-1770.html",
      "source": "reinasex"
    },
    {
      "name": "村上涼子さん（@murakamiryoko） - きれいなお姉さん無修正",
      "id": "murakamiryoko",
      "insta": "",
      "images": [
        "https://x8.shinobi.jp/bin/ll?100057901",
        "https://blog-imgs-145-origin.2nt.com/r/e/i/reinasex/050825_100s.jpg",
        "https://blog-imgs-145-origin.2nt.com/r/e/i/reinasex/050825_100-1s.jpg"
      ],
      "url": "https://reinasex.blog.2nt.com/blog-entry-1584.html",
      "source": "reinasex"
    },
    {
      "name": "芹沢まゆら（佐野絵美）さん - きれいなお姉さん無修正",
      "id": "iCHig0mARchEn",
      "insta": "",
      "images": [
        "https://x8.shinobi.jp/bin/ll?100057901",
        "https://blog-imgs-145-origin.2nt.com/r/e/i/reinasex/emi-sano-1-1s.jpg",
        "https://blog-imgs-145-origin.2nt.com/r/e/i/reinasex/emi-sano-1-2s.jpg"
      ],
      "url": "https://reinasex.blog.2nt.com/blog-entry-1670.html",
      "source": "reinasex"
    },
    {
      "name": "江波りゅう（@ryu_enami）さん - きれいなお姉さん無修正",
      "id": "ryu_enami",
      "insta": "",
      "images": [
        "https://x8.shinobi.jp/bin/ll?100057901",
        "https://blog-imgs-145-origin.2nt.com/r/e/i/reinasex/121825_001s.jpg",
        "https://jjgirls.com/uncensored/1pondo/ryu-eba/121825_001/ryu-eba-1.jpg"
      ],
      "url": "https://reinasex.blog.2nt.com/blog-entry-1753.html",
      "source": "reinasex"
    },
    {
      "name": "向井藍♠（@ai_mukaiAV）さん - きれいなお姉さん無修正",
      "id": "ai_mukaiAV",
      "insta": "https://www.instagram.com/muuchan1024/",
      "images": [
        "https://x8.shinobi.jp/bin/ll?100057901",
        "https://blog-imgs-145-origin.2nt.com/r/e/i/reinasex/tokyohot-n1170s.jpg",
        "https://jjgirls.com/japanese/mari-haneda/12/mari-haneda-3.jpg"
      ],
      "url": "https://reinasex.blog.2nt.com/blog-entry-1754.html",
      "source": "reinasex"
    },
    {
      "name": "Lexi Lore（@MoreLexiLore）さん - きれいなお姉さん無修正",
      "id": "MoreLexiLore",
      "insta": "https://www.instagram.com/lexiloreonyoutube/",
      "images": [
        "https://x8.shinobi.jp/bin/ll?100057901",
        "https://blog-imgs-145-origin.2nt.com/r/e/i/reinasex/LexiLore-Blacked-Blueprint-31s.jpg",
        "https://blog-imgs-145-origin.2nt.com/r/e/i/reinasex/LexiLore-Blacked-Blueprint-35s.jpg"
      ],
      "url": "https://reinasex.blog.2nt.com/blog-entry-1749.html",
      "source": "reinasex"
    },
    {
      "name": "如月結衣(咲々原リン)さん - きれいなお姉さん無修正",
      "id": "nanase_m0511",
      "insta": "https://www.instagram.com/nanase.0511/",
      "images": [
        "https://x8.shinobi.jp/bin/ll?100057901",
        "https://blog-imgs-145-origin.2nt.com/r/e/i/reinasex/heyzo-2265s.jpg",
        "https://jjgirls.com/uncensored/heyzo/yui-kisaragi/2265/yui-kisaragi-1.jpg"
      ],
      "url": "https://reinasex.blog.2nt.com/blog-entry-1649.html",
      "source": "reinasex"
    },
    {
      "name": "星野あいか（@aikahoshinooo）さん - きれいなお姉さん無修正",
      "id": "profile",
      "insta": "https://www.instagram.com/aikahoshinooo/",
      "images": [
        "https://x8.shinobi.jp/bin/ll?100057901",
        "https://blog-imgs-145-origin.2nt.com/r/e/i/reinasex/050425_001s.jpg",
        "https://jjgirls.com/uncensored/1pondo/aika-hoshino/050425_001/aika-hoshino-1.jpg"
      ],
      "url": "https://reinasex.blog.2nt.com/blog-entry-1634.html",
      "source": "reinasex"
    },
    {
      "name": "双葉みおさん（@ne_tiara） - きれいなお姉さん無修正",
      "id": "ne_tiara",
      "insta": "https://www.instagram.com/miofutaba/",
      "images": [
        "https://x8.shinobi.jp/bin/ll?100057901",
        "https://blog-imgs-145-origin.2nt.com/r/e/i/reinasex/030425_001.jpg",
        "https://jjgirls.com/uncensored/1pondo/mio-hutaba/030425_001/mio-hutaba-1.jpg"
      ],
      "url": "https://reinasex.blog.2nt.com/blog-entry-1740.html",
      "source": "reinasex"
    },
    {
      "name": "真名瀬りかさん（櫻木梨乃さん） - きれいなお姉さん無修正",
      "id": "emiri_rino",
      "insta": "https://www.instagram.com/sakuragirino",
      "images": [
        "https://x8.shinobi.jp/bin/ll?100057901",
        "https://blog-imgs-145-origin.2nt.com/r/e/i/reinasex/011921-001s.jpg",
        "https://jjgirls.com/uncensored/caribbeancom/rino-sakuragi/011921-001/rino-sakuragi-1.jpg"
      ],
      "url": "https://reinasex.blog.2nt.com/blog-entry-1567.html",
      "source": "reinasex"
    },
    {
      "name": "佐倉みこさん（桜もこさん） - きれいなお姉さん無修正",
      "id": "moko_sakura3",
      "insta": "https://www.instagram.com/mokochan319/",
      "images": [
        "https://x8.shinobi.jp/bin/ll?100057901",
        "https://blog-imgs-145-origin.2nt.com/r/e/i/reinasex/032126-001xs.jpg",
        "https://blog-imgs-501-origin.2nt.com/c/u/t/cutiepussy1/2024704302040912171.jpg"
      ],
      "url": "https://reinasex.blog.2nt.com/blog-entry-1742.html",
      "source": "reinasex"
    },
    {
      "name": "新城由衣（寿々野美花）さんと明日香クレア（椎名あすか）さん - きれいなお姉さん無修正",
      "id": "claireaka2",
      "insta": "https://www.instagram.com/claire.a.ka/",
      "images": [
        "https://x8.shinobi.jp/bin/ll?100057901",
        "https://blog-imgs-145-origin.2nt.com/r/e/i/reinasex/041021_001s.jpg",
        "https://jjgirls.com/uncensored/1pondo/asuka-shiina/041021_001/asuka-shiina-1.jpg"
      ],
      "url": "https://reinasex.blog.2nt.com/blog-entry-1748.html",
      "source": "reinasex"
    },
    {
      "name": "前田由美さん（藤森里穂さん） - きれいなお姉さん無修正",
      "id": "fujimoriho123",
      "insta": "https://www.instagram.com/fujimoriho123/",
      "images": [
        "https://x8.shinobi.jp/bin/ll?100057901",
        "https://blog-imgs-145-origin.2nt.com/r/e/i/reinasex/101114-709s.jpg",
        "https://jjgirls.com/uncensored/caribbeancom/yumi-maeda/101114-709/yumi-maeda-1.jpg"
      ],
      "url": "https://reinasex.blog.2nt.com/blog-entry-1577.html",
      "source": "reinasex"
    },
    {
      "name": "水川スミレさん（百多えみりさん） (@mizukawasumire) - きれいなお姉さん無修正",
      "id": "momotaemiri",
      "insta": "https://www.instagram.com/mizukawasumireworld/",
      "images": [
        "https://x8.shinobi.jp/bin/ll?100057901",
        "https://blog-imgs-145-origin.2nt.com/r/e/i/reinasex/Emiri-Momota-BBC-Pleasure-02s.jpg",
        "https://blog-imgs-145-origin.2nt.com/r/e/i/reinasex/Emiri-Momota-BBC-Pleasure-15s.jpg"
      ],
      "url": "https://reinasex.blog.2nt.com/blog-entry-1665.html",
      "source": "reinasex"
    },
    {
      "name": "メロディー・雛・マークスさん - きれいなお姉さん無修正",
      "id": "MelodyMarksxxx",
      "insta": "https://www.instagram.com/melodymarksxxofficial/",
      "images": [
        "https://x8.shinobi.jp/bin/ll?100057901",
        "https://blog-imgs-145-origin.2nt.com/r/e/i/reinasex/MelodyMarks-Nubiles-Orgasm-02s.jpg",
        "https://x.jjj.cam/pics/nubiles/melody-marks/sexist-white-hairy-pussy-xxxpictures/melody-marks-6.jpg"
      ],
      "url": "https://reinasex.blog.2nt.com/blog-entry-1505.html",
      "source": "reinasex"
    },
    {
      "name": "弘中れおなさん（@hirose_riona） - きれいなお姉さん無修正",
      "id": "hirose_riona",
      "insta": "https://www.instagram.com/hirose_riona1210/",
      "images": [
        "https://x8.shinobi.jp/bin/ll?100057901",
        "https://blog-imgs-145-origin.2nt.com/r/e/i/reinasex/011026_001s.jpg",
        "https://blog-imgs-145-origin.2nt.com/r/e/i/reinasex/011026_001-001s.jpg"
      ],
      "url": "https://reinasex.blog.2nt.com/blog-entry-1720.html",
      "source": "reinasex"
    },
    {
      "name": "佐倉みこさん（桜もこさん） - きれいなお姉さん無修正",
      "id": "moko_sakura3",
      "insta": "https://www.instagram.com/mokochan319/",
      "images": [
        "https://x8.shinobi.jp/bin/ll?100057901",
        "https://blog-imgs-145-origin.2nt.com/r/e/i/reinasex/022126-001-001x.jpg",
        "https://blog-imgs-145-origin.2nt.com/r/e/i/reinasex/022126-001-002x.jpg"
      ],
      "url": "https://reinasex.blog.2nt.com/blog-entry-1718.html",
      "source": "reinasex"
    },
    {
      "name": "宇野かな美（金谷うの）さん - きれいなお姉さん無修正",
      "id": "secretsexydoll_",
      "insta": "",
      "images": [
        "https://x8.shinobi.jp/bin/ll?100057901",
        "https://blog-imgs-145-origin.2nt.com/r/e/i/reinasex/050225_001s.jpg",
        "https://jjgirls.com/uncensored/1pondo/kanami-uno/050225_001/kanami-uno-1.jpg"
      ],
      "url": "https://reinasex.blog.2nt.com/blog-entry-1708.html",
      "source": "reinasex"
    },
    {
      "name": "百合川さら（@yurikawa_sara）さん - きれいなお姉さん無修正",
      "id": "yurikawa_sara",
      "insta": "https://www.instagram.com/yurikawa_sara/",
      "images": [
        "https://x8.shinobi.jp/bin/ll?100057901",
        "https://blog-imgs-145-origin.2nt.com/r/e/i/reinasex/heyzo-0936s.jpg",
        "https://jjgirls.com/uncensored/heyzo/sara-yurikawa/0936/sara-yurikawa-1.jpg"
      ],
      "url": "https://reinasex.blog.2nt.com/blog-entry-1717.html",
      "source": "reinasex"
    },
    {
      "name": "横山みれいさん（@mirei_y） - きれいなお姉さん無修正",
      "id": "mirei_y",
      "insta": "https://www.instagram.com/mireichan66/",
      "images": [
        "https://x8.shinobi.jp/bin/ll?100057901",
        "https://blog-imgs-145-origin.2nt.com/r/e/i/reinasex/030913_547s.jpg",
        "https://blog-imgs-145-origin.2nt.com/r/e/i/reinasex/062013_612s.jpg"
      ],
      "url": "https://reinasex.blog.2nt.com/blog-entry-1167.html",
      "source": "reinasex"
    },
    {
      "name": "Kazumi（@kazumisworld） - きれいなお姉さん無修正",
      "id": "kazumisworld",
      "insta": "https://www.instagram.com/kazumisworld/",
      "images": [
        "https://x8.shinobi.jp/bin/ll?100057901",
        "https://blog-imgs-145-origin.2nt.com/r/e/i/reinasex/Kazumi-Blackedraw-Beast-010s.jpg",
        "https://blog-imgs-145-origin.2nt.com/r/e/i/reinasex/Kazumi-Blackedraw-Beast-052s.jpg"
      ],
      "url": "https://reinasex.blog.2nt.com/blog-entry-1550.html",
      "source": "reinasex"
    },
    {
      "name": "水野葵",
      "id": "reina_1472",
      "insta": "",
      "images": [
        "https://x8.shinobi.jp/bin/ll?100057901",
        "https://blog-imgs-145-origin.2nt.com/r/e/i/reinasex/011615-786-001.jpg",
        "https://blog-imgs-145-origin.2nt.com/r/e/i/reinasex/011615-786-002s.jpg"
      ],
      "url": "https://reinasex.blog.2nt.com/blog-entry-1472.html",
      "source": "reinasex"
    },
    {
      "name": "浅田真美",
      "id": "reina_1774",
      "insta": "",
      "images": [
        "https://x8.shinobi.jp/bin/ll?100057901",
        "https://blog-imgs-145-origin.2nt.com/r/e/i/reinasex/052315_085s.jpg",
        "https://blog-imgs-145-origin.2nt.com/r/e/i/reinasex/060416_311s.jpg"
      ],
      "url": "https://reinasex.blog.2nt.com/blog-entry-1774.html",
      "source": "reinasex"
    },
    {
      "name": "汝鳥すみか",
      "id": "reina_1768",
      "insta": "",
      "images": [
        "https://x8.shinobi.jp/bin/ll?100057901",
        "https://blog-imgs-145-origin.2nt.com/r/e/i/reinasex/sumika-natori-1-7s.jpg",
        "https://blog-imgs-145-origin.2nt.com/r/e/i/reinasex/sumika-natori-1-8s.jpg"
      ],
      "url": "https://reinasex.blog.2nt.com/blog-entry-1768.html",
      "source": "reinasex"
    },
    {
      "name": "斉木ゆあ",
      "id": "reina_1579",
      "insta": "",
      "images": [
        "https://x8.shinobi.jp/bin/ll?100057901",
        "https://blog-imgs-145-origin.2nt.com/r/e/i/reinasex/072514_850s.jpg",
        "https://jjgirls.com/uncensored/1pondo/ami-saiki/072514_850/ami-saiki-16.jpg"
      ],
      "url": "https://reinasex.blog.2nt.com/blog-entry-1579.html",
      "source": "reinasex"
    },
    {
      "name": "桐生さくら",
      "id": "reina_1486",
      "insta": "https://www.instagram.com/kiryu.sakura_official/",
      "images": [
        "https://x8.shinobi.jp/bin/ll?100057901",
        "https://jjgirls.com/japanese/misaki-matsushita/7/misaki-matsushita-5.jpg",
        "https://blog-imgs-145-origin.2nt.com/r/e/i/reinasex/misaki-matsushita-7-12s.jpg"
      ],
      "url": "https://reinasex.blog.2nt.com/blog-entry-1486.html",
      "source": "reinasex"
    },
    {
      "name": "七原菜々子",
      "id": "reina_1759",
      "insta": "",
      "images": [
        "https://x8.shinobi.jp/bin/ll?100057901",
        "https://blog-imgs-145-origin.2nt.com/r/e/i/reinasex/SpermMania-NanaharaNanako-238-13s.jpg",
        "https://blog-imgs-145-origin.2nt.com/r/e/i/reinasex/SpermMania-NanaharaNanako-238-14s.jpg"
      ],
      "url": "https://reinasex.blog.2nt.com/blog-entry-1759.html",
      "source": "reinasex"
    },
    {
      "name": "流川紗奈（流川千穂）",
      "id": "reina_1757",
      "insta": "",
      "images": [
        "https://x8.shinobi.jp/bin/ll?100057901",
        "https://blog-imgs-145-origin.2nt.com/r/e/i/reinasex/heyzo-3764.jpg",
        "https://jjgirls.com/uncensored/heyzo/sana-rukawa/3764/sana-rukawa-1.jpg"
      ],
      "url": "https://reinasex.blog.2nt.com/blog-entry-1757.html",
      "source": "reinasex"
    },
    {
      "name": "さくらみな",
      "id": "reina_1744",
      "insta": "",
      "images": [
        "https://x8.shinobi.jp/bin/ll?100057901",
        "https://blog-imgs-145-origin.2nt.com/r/e/i/reinasex/050424_001s.jpg",
        "https://jjgirls.com/uncensored/1pondo/mina-sakura/050424_001/mina-sakura-1.jpg"
      ],
      "url": "https://reinasex.blog.2nt.com/blog-entry-1744.html",
      "source": "reinasex"
    },
    {
      "name": "上山奈々",
      "id": "reina_1745",
      "insta": "",
      "images": [
        "https://x8.shinobi.jp/bin/ll?100057901",
        "https://blog-imgs-145-origin.2nt.com/r/e/i/reinasex/110525-001s.jpg",
        "https://jjgirls.com/uncensored/caribbeancom/nana-kamiyama/110525-001/nana-kamiyama-1.jpg"
      ],
      "url": "https://reinasex.blog.2nt.com/blog-entry-1745.html",
      "source": "reinasex"
    },
    {
      "name": "真咲レイ",
      "id": "reina_1636",
      "insta": "",
      "images": [
        "https://x8.shinobi.jp/bin/ll?100057901",
        "https://blog-imgs-145-origin.2nt.com/r/e/i/reinasex/rei-takagaki-14-10s.jpg",
        "https://blog-imgs-145-origin.2nt.com/r/e/i/reinasex/rei-takagaki-15-1s.jpg"
      ],
      "url": "https://reinasex.blog.2nt.com/blog-entry-1636.html",
      "source": "reinasex"
    },
    {
      "name": "本多まい",
      "id": "reina_1746",
      "insta": "",
      "images": [
        "https://x8.shinobi.jp/bin/ll?100057901",
        "https://blog-imgs-145-origin.2nt.com/r/e/i/reinasex/020126_001.jpg",
        "https://jjgirls.com/uncensored/1pondo/mai-honda/020126_001/mai-honda-1.jpg"
      ],
      "url": "https://reinasex.blog.2nt.com/blog-entry-1746.html",
      "source": "reinasex"
    },
    {
      "name": "大橋未久",
      "id": "reina_1668",
      "insta": "",
      "images": [
        "https://x8.shinobi.jp/bin/ll?100057901",
        "https://blog-imgs-145-origin.2nt.com/r/e/i/reinasex/120214-749s.jpg",
        "https://jjgirls.com/uncensored/caribbeancom/miku-oohashi/120214-749/miku-oohashi-1.jpg"
      ],
      "url": "https://reinasex.blog.2nt.com/blog-entry-1668.html",
      "source": "reinasex"
    },
    {
      "name": "河西ちなみ(西河みなみ)",
      "id": "reina_1456",
      "insta": "",
      "images": [
        "https://x8.shinobi.jp/bin/ll?100057901",
        "https://blog-imgs-145-origin.2nt.com/r/e/i/reinasex/minami-nishikawa-18-11.jpg",
        "https://blog-imgs-145-origin.2nt.com/r/e/i/reinasex/minami-nishikawa-21-8.jpg"
      ],
      "url": "https://reinasex.blog.2nt.com/blog-entry-1456.html",
      "source": "reinasex"
    },
    {
      "name": "秋山陽菜",
      "id": "reina_1390",
      "insta": "",
      "images": [
        "https://x8.shinobi.jp/bin/ll?100057901",
        "https://blog-imgs-145-origin.2nt.com/r/e/i/reinasex/yuna-akiyama-34-4s.jpg",
        "https://blog-imgs-145-origin.2nt.com/r/e/i/reinasex/yuna-akiyama-34-5s.jpg"
      ],
      "url": "https://reinasex.blog.2nt.com/blog-entry-1390.html",
      "source": "reinasex"
    },
    {
      "name": "河愛杏里",
      "id": "reina_1710",
      "insta": "",
      "images": [
        "https://x8.shinobi.jp/bin/ll?100057901",
        "https://blog-imgs-145-origin.2nt.com/r/e/i/reinasex/anri-kawai-28-1s.jpg",
        "https://jjgirls.com/japanese/anri-kawai/28/anri-kawai-9.jpg"
      ],
      "url": "https://reinasex.blog.2nt.com/blog-entry-1710.html",
      "source": "reinasex"
    },
    {
      "name": "宮高艶子",
      "id": "reina_1521",
      "insta": "",
      "images": [
        "https://x8.shinobi.jp/bin/ll?100057901",
        "https://blog-imgs-145-origin.2nt.com/r/e/i/reinasex/tsuyako-miyataka-1-1s.jpg",
        "https://blog-imgs-145-origin.2nt.com/r/e/i/reinasex/tsuyako-miyataka-1-3s.jpg"
      ],
      "url": "https://reinasex.blog.2nt.com/blog-entry-1521.html",
      "source": "reinasex"
    },
    {
      "name": "小高里保",
      "id": "reina_1728",
      "insta": "",
      "images": [
        "https://x8.shinobi.jp/bin/ll?100057901",
        "https://blog-imgs-145-origin.2nt.com/r/e/i/reinasex/tokyohot-n1199s.jpg",
        "https://blog-imgs-145-origin.2nt.com/r/e/i/reinasex/heyzo-1194s.jpg"
      ],
      "url": "https://reinasex.blog.2nt.com/blog-entry-1728.html",
      "source": "reinasex"
    },
    {
      "name": "一条リオン",
      "id": "reina_1722",
      "insta": "",
      "images": [
        "https://x8.shinobi.jp/bin/ll?100057901",
        "https://blog-imgs-145-origin.2nt.com/r/e/i/reinasex/091016-254s.jpg",
        "https://jjgirls.com/uncensored/caribbeancom/rion-ichijo/091016-254/rion-ichijo-1.jpg"
      ],
      "url": "https://reinasex.blog.2nt.com/blog-entry-1722.html",
      "source": "reinasex"
    },
    {
      "name": "司よう子",
      "id": "reina_1562",
      "insta": "",
      "images": [
        "https://x8.shinobi.jp/bin/ll?100057901",
        "https://blog-imgs-145-origin.2nt.com/r/e/i/reinasex/020223_001s.jpg",
        "https://jjgirls.com/uncensored/1pondo/eri-saeki/020223_001/eri-saeki-1.jpg"
      ],
      "url": "https://reinasex.blog.2nt.com/blog-entry-1562.html",
      "source": "reinasex"
    },
    {
      "name": "蒼木マナ",
      "id": "reina_1586",
      "insta": "",
      "images": [
        "https://x8.shinobi.jp/bin/ll?100057901",
        "https://blog-imgs-145-origin.2nt.com/r/e/i/reinasex/mei-namiki-17-10s.jpg",
        "https://blog-imgs-145-origin.2nt.com/r/e/i/reinasex/mei-namiki-17-11s.jpg"
      ],
      "url": "https://reinasex.blog.2nt.com/blog-entry-1586.html",
      "source": "reinasex"
    },
    {
      "name": "白咲舞",
      "id": "reina_1617",
      "insta": "",
      "images": [
        "https://x8.shinobi.jp/bin/ll?100057901",
        "https://blog-imgs-145-origin.2nt.com/r/e/i/reinasex/052512_346s.jpg",
        "https://blog-imgs-145-origin.2nt.com/r/e/i/reinasex/052512_346-1s.jpg"
      ],
      "url": "https://reinasex.blog.2nt.com/blog-entry-1617.html",
      "source": "reinasex"
    },
    {
      "name": "佐野美鈴",
      "id": "reina_1711",
      "insta": "",
      "images": [
        "https://x8.shinobi.jp/bin/ll?100057901",
        "https://blog-imgs-145-origin.2nt.com/r/e/i/reinasex/misuzu-sano-1-10s.jpg",
        "https://blog-imgs-145-origin.2nt.com/r/e/i/reinasex/misuzu-sano-2-2s.jpg"
      ],
      "url": "https://reinasex.blog.2nt.com/blog-entry-1711.html",
      "source": "reinasex"
    },
    {
      "name": "今田美玲",
      "id": "reina_1709",
      "insta": "",
      "images": [
        "https://x8.shinobi.jp/bin/ll?100057901",
        "https://blog-imgs-145-origin.2nt.com/r/e/i/reinasex/042923_001s.jpg",
        "https://blog-imgs-145-origin.2nt.com/r/e/i/reinasex/070423_001s.jpg"
      ],
      "url": "https://reinasex.blog.2nt.com/blog-entry-1709.html",
      "source": "reinasex"
    },
    {
      "name": "青山茉悠",
      "id": "reina_1703",
      "insta": "",
      "images": [
        "https://x8.shinobi.jp/bin/ll?100057901",
        "https://blog-imgs-145-origin.2nt.com/r/e/i/reinasex/022225_001s.jpg",
        "https://jjgirls.com/uncensored/1pondo/mayu-aoyama/022225_001/mayu-aoyama-1.jpg"
      ],
      "url": "https://reinasex.blog.2nt.com/blog-entry-1703.html",
      "source": "reinasex"
    },
    {
      "name": "北村沙織",
      "id": "reina_1699",
      "insta": "",
      "images": [
        "https://x8.shinobi.jp/bin/ll?100057901",
        "https://blog-imgs-145-origin.2nt.com/r/e/i/reinasex/saori-kitamura-1-7.jpg",
        "https://jjgirls.com/japanese/saori-kitamura/1/saori-kitamura-3.jpg"
      ],
      "url": "https://reinasex.blog.2nt.com/blog-entry-1699.html",
      "source": "reinasex"
    }
  ]
}